vtuberwiki/__init__.py
vtuberwiki/aiovwiki.py
vtuberwiki/vwiki.py
vtuberwiki_py-0.1.8.dist-info/LICENSE
vtuberwiki_py-0.1.8.dist-info/METADATA
vtuberwiki_py-0.1.8.dist-info/WHEEL
vtuberwiki_py-0.1.8.dist-info/top_level.txt
vtuberwiki_py-0.1.8.dist-info/RECORD
