Metadata-Version: 2.1
Name: vtuberwiki-py
Version: 0.1.8
Summary: vtuberwiki-py is a Python wrapper for VirtualYoutuber Fandom API.
Home-page: https://github.com/daffpy/vtuberwiki-py
Author: Daffa
Author-email: codingdaffa@gmail.com
License: MIT
Keywords: python wikia virtualyoutuber fandom API
Platform: UNKNOWN
Classifier: License :: OSI Approved :: MIT License
Classifier: Programming Language :: Python :: 3.7
Classifier: Programming Language :: Python :: 3.8
Classifier: Programming Language :: Python :: 3.9
Requires-Dist: lxml
Requires-Dist: aiohttp
Requires-Dist: beautifulsoup4
Requires-Dist: requests
Requires-Dist: cchardet
